cliBattleship/__init__.py
cliBattleship/cliBattleship.py
cliBattleship/gameModules/__init__.py
cliBattleship/gameModules/autoShipPlacement.py
cliBattleship/gameModules/computerPlays.py
cliBattleship/gameModules/gameBoards.py
cliBattleship/gameModules/gameFunctions.py
cliBattleship/gameModules/playerNumberFunctions.py
cliBattleship/gameModules/playerPlays.py
cliBattleship/gameModules/playerShipPlacement.py
cliBattleship/gameModules/players.py
cliBattleship-0.0.5.dist-info/LICENSE.txt
cliBattleship-0.0.5.dist-info/METADATA
cliBattleship-0.0.5.dist-info/WHEEL
cliBattleship-0.0.5.dist-info/top_level.txt
cliBattleship-0.0.5.dist-info/RECORD
